TottyEphys/__init__.py
TottyEphys/io.py
TottyEphys/visualize.py
TottyEphys-0.1.dist-info/LICENSE
TottyEphys-0.1.dist-info/METADATA
TottyEphys-0.1.dist-info/WHEEL
TottyEphys-0.1.dist-info/top_level.txt
TottyEphys-0.1.dist-info/RECORD
