Metadata-Version: 2.1
Name: TottyEphys
Version: 0.1
Summary: A package containing helper functions for in vivo ephys data analysis
Home-page: https://github.com/mictott/TottyEphys
Author: Michael Totty
Author-email: mictott@gmail.com
License-File: LICENSE
Requires-Dist: numpy
Requires-Dist: matplotlib
Requires-Dist: pandas
Requires-Dist: quantities
Requires-Dist: xarray
Requires-Dist: elephant
Requires-Dist: tqdm
Requires-Dist: pynapple
Requires-Dist: pyprojroot
